{
  "daily": [
    {
      "groupId": 1002,
      "tasks": [
        {
          "id": 100201,
          "name": "每日扎一会",
          "desc": "每日扎一会，开开心心拿金币",
          "target": 10,
          "icon": "",
          "roomId": [],
          "type": "battle",
          "grant": 588
        }
      ]
    },
    {
      "groupId": 1004,
      "tasks": [
        {
          "id": 100401,
          "name": "每日开一会",
          "desc": "开会1把，可获得任务奖励",
          "target": 1,
          "icon": "",
          "roomId": [],
          "type": "meeting",
          "grant": 888
        }
      ]
    },
    {
      "groupId": 1011,
      "tasks": [
        {
          "id": 101101,
          "name": "每日赢10把",
          "desc": "每日赢10把，开开心心拿金币",
          "target": 10,
          "icon": "",
          "roomId": [],
          "type": "win",
          "grant": 888
        }
      ]
    }
  ],
  "forever": [
    {
      "groupId": 3005,
      "tasks": [
        {
          "id": 300501,
          "name": "对战3把",
          "desc": "对战3把，可获得任务奖励",
          "target": 3,
          "icon": "",
          "roomId": [],
          "type": "battle",
          "grant": 300
        },
        {
          "id": 300502,
          "name": "对战10把",
          "desc": "对战10把，可获得任务奖励",
          "target": 10,
          "icon": "",
          "roomId": [],
          "type": "battle",
          "grant": 500
        },
        {
          "id": 300503,
          "name": "对战50把",
          "desc": "对战50把，可获得任务奖励",
          "target": 50,
          "icon": "",
          "roomId": [],
          "type": "battle",
          "grant": 1500
        },
        {
          "id": 300504,
          "name": "对战100把",
          "desc": "对战100把，可获得任务奖励",
          "target": 100,
          "icon": "",
          "roomId": [],
          "type": "battle",
          "grant": 3000
        },
        {
          "id": 300505,
          "name": "对战500把",
          "desc": "对战500把，可获得任务奖励",
          "target": 500,
          "icon": "",
          "roomId": [],
          "type": "battle",
          "grant": 4000
        },
        {
          "id": 300506,
          "name": "对战1000把",
          "desc": "对战1000把，可获得任务奖励",
          "target": 1000,
          "icon": "",
          "roomId": [],
          "type": "battle",
          "grant": 5000
        }
      ]
    },
    {
      "groupId": 3004,
      "tasks": [
        {
          "id": 300401,
          "name": "胜利3把",
          "desc": "胜利3把，可获得任务奖励",
          "target": 3,
          "icon": "",
          "roomId": [],
          "type": "win",
          "grant": 500
        },
        {
          "id": 300402,
          "name": "胜利10把",
          "desc": "胜利10把，可获得任务奖励",
          "target": 10,
          "icon": "",
          "roomId": [],
          "type": "win",
          "grant": 1288
        },
        {
          "id": 300403,
          "name": "胜利30把",
          "desc": "胜利30把，可获得任务奖励",
          "target": 30,
          "icon": "",
          "roomId": [],
          "type": "win",
          "grant": 1888
        },
        {
          "id": 300404,
          "name": "胜利50把",
          "desc": "胜利50把，可获得任务奖励",
          "target": 50,
          "icon": "",
          "roomId": [],
          "type": "win",
          "grant": 2888
        },
        {
          "id": 300405,
          "name": "胜利100把",
          "desc": "胜利100把，可获得任务奖励",
          "target": 100,
          "icon": "",
          "roomId": [],
          "type": "win",
          "grant": 3888
        },
        {
          "id": 300406,
          "name": "胜利500把",
          "desc": "胜利500把，可获得任务奖励",
          "target": 500,
          "icon": "",
          "roomId": [],
          "type": "win",
          "grant": 4888
        },
        {
          "id": 300407,
          "name": "胜利1000把",
          "desc": "胜利1000把，可获得任务奖励",
          "target": 1000,
          "icon": "",
          "roomId": [],
          "type": "win",
          "grant": 6888
        }
      ]
    },
    {
      "groupId": 3003,
      "tasks": [
        {
          "id": 300301,
          "name": "在元宝场对战10把",
          "desc": "对战10把，可获得任务奖励",
          "target": 10,
          "icon": "",
          "roomId": [
            13,
            23,
            33,
            14,
            24,
            34
          ],
          "type": "battle",
          "grant": 1388
        },
        {
          "id": 300302,
          "name": "在元宝场对战50把",
          "desc": "对战50把，可获得任务奖励",
          "target": 50,
          "icon": "",
          "roomId": [
            13,
            23,
            33,
            14,
            24,
            34
          ],
          "type": "battle",
          "grant": 2388
        },
        {
          "id": 300303,
          "name": "在元宝场对战100把",
          "desc": "对战100把，可获得任务奖励",
          "target": 100,
          "icon": "",
          "roomId": [
            13,
            23,
            33,
            14,
            24,
            34
          ],
          "type": "battle",
          "grant": 3388
        },
        {
          "id": 300304,
          "name": "在元宝场对战500把",
          "desc": "对战500把，可获得任务奖励",
          "target": 500,
          "icon": "",
          "roomId": [
            13,
            23,
            33,
            14,
            24,
            34
          ],
          "type": "battle",
          "grant": 5888
        },
        {
          "id": 300305,
          "name": "在元宝场对战1000把",
          "desc": "对战1000把，可获得任务奖励",
          "target": 1000,
          "icon": "",
          "roomId": [
            13,
            23,
            33,
            14,
            24,
            34
          ],
          "type": "battle",
          "grant": 8888
        }
      ]
    },
    {
      "groupId": 3002,
      "tasks": [
        {
          "id": 300201,
          "name": "在元宝场胜利10把",
          "desc": "胜利10把，可获得任务奖励",
          "target": 10,
          "icon": "",
          "roomId": [
            13,
            23,
            33,
            14,
            24,
            34
          ],
          "type": "win",
          "grant": 2888
        },
        {
          "id": 300202,
          "name": "在元宝场胜利50把",
          "desc": "胜利50把，可获得任务奖励",
          "target": 50,
          "icon": "",
          "roomId": [
            13,
            23,
            33,
            14,
            24,
            34
          ],
          "type": "win",
          "grant": 3888
        },
        {
          "id": 300203,
          "name": "在元宝场胜利100把",
          "desc": "胜利100把，可获得任务奖励",
          "target": 100,
          "icon": "",
          "roomId": [
            13,
            23,
            33,
            14,
            24,
            34
          ],
          "type": "win",
          "grant": 5888
        },
        {
          "id": 300204,
          "name": "在元宝场胜利500把",
          "desc": "胜利500把，可获得任务奖励",
          "target": 500,
          "icon": "",
          "roomId": [
            13,
            23,
            33,
            14,
            24,
            34
          ],
          "type": "win",
          "grant": 8888
        },
        {
          "id": 300205,
          "name": "在元宝场胜利1000把",
          "desc": "胜利1000把，可获得任务奖励",
          "target": 1000,
          "icon": "",
          "roomId": [
            13,
            23,
            33,
            14,
            24,
            34
          ],
          "type": "win",
          "grant": 10000
        }
      ]
    },
    {
      "groupId": 2002,
      "tasks": [
        {
          "id": 200201,
          "name": "开会1把",
          "desc": "开会1把，可获得任务奖励",
          "target": 1,
          "icon": "",
          "roomId": [],
          "type": "meeting",
          "grant": 600
        },
        {
          "id": 200202,
          "name": "开会10把",
          "desc": "开会10把，可获得任务奖励",
          "target": 10,
          "icon": "",
          "roomId": [],
          "type": "meeting",
          "grant": 2000
        },
        {
          "id": 200203,
          "name": "开会30把",
          "desc": "开会30把，可获得任务奖励",
          "target": 30,
          "icon": "",
          "roomId": [],
          "type": "meeting",
          "grant": 3000
        },
        {
          "id": 200204,
          "name": "开会100把",
          "desc": "开会100把，可获得任务奖励",
          "target": 100,
          "icon": "",
          "roomId": [],
          "type": "meeting",
          "grant": 10000
        }
      ]
    },
    {
      "groupId": 2001,
      "tasks": [
        {
          "id": 200101,
          "name": "在元宝场开会5把",
          "desc": "开会5把，可获得任务奖励",
          "target": 5,
          "icon": "",
          "roomId": [
            13,
            23,
            33
          ],
          "type": "meeting",
          "grant": 1500
        },
        {
          "id": 200102,
          "name": "在元宝场开会20把",
          "desc": "开会20把，可获得任务奖励",
          "target": 20,
          "icon": "",
          "roomId": [
            13,
            23,
            33
          ],
          "type": "meeting",
          "grant": 3000
        },
        {
          "id": 200103,
          "name": "在高手PK房间开会50把",
          "desc": "开会50把，可获得任务奖励",
          "target": 50,
          "icon": "",
          "roomId": [
            13,
            23,
            33
          ],
          "type": "meeting",
          "grant": 5000
        }
      ]
    },
    {
      "groupId": 4001,
      "tasks": [
        {
          "id": 400101,
          "name": "赢元宝",
          "desc": "在元宝场1000底注赢30把，可获得1枚元宝",
          "target": 30,
          "icon": "",
          "roomId": [
            13,
            23,
            33
          ],
          "type": "win",
          "grant": 0,
          "fragment": 1
        }
      ]
    },
    {
      "groupId": 4002,
      "tasks": [
        {
          "id": 400201,
          "name": "赢元宝 - 快速",
          "desc": "在元宝场5000底注赢15把，可获得1枚元宝",
          "target": 15,
          "icon": "",
          "roomId": [
            14
          ],
          "type": "win",
          "grant": 0,
          "fragment": 1
        }
      ]
    }
  ]
}